rev/__init__.py
rev/py.typed
rev/rev.cpp
rev/sparkbaseconfig_apply.h
rev/version.py
rev/_init__rev.py
rev/_rev.cp312-win_amd64.lib
rev/_rev.cp312-win_amd64.pyd
rev/_rev.pyi
rev/rev.pc
rev/trampolines/__StatusLogger.hpp
rev/trampolines/rev__AbsoluteEncoder.hpp
rev/trampolines/rev__AnalogInput.hpp
rev/trampolines/rev__BaseConfig.hpp
rev/trampolines/rev__CIEColor.hpp
rev/trampolines/rev__ColorMatch.hpp
rev/trampolines/rev__ColorSensorV3.hpp
rev/trampolines/rev__ColorSensorV3__RawColor.hpp
rev/trampolines/rev__RelativeEncoder.hpp
rev/trampolines/rev__detached__DetachedEncoder.hpp
rev/trampolines/rev__detached__DetachedEncoderConfig.hpp
rev/trampolines/rev__detached__DetachedEncoderConfigAccessor.hpp
rev/trampolines/rev__detached__DetachedEncoderLowLevel.hpp
rev/trampolines/rev__detached__DetachedEncoderLowLevel__FirmwareVersion.hpp
rev/trampolines/rev__detached__DetachedEncoderLowLevel__PeriodicStatus0.hpp
rev/trampolines/rev__detached__DetachedEncoderLowLevel__PeriodicStatus1.hpp
rev/trampolines/rev__detached__DetachedEncoderLowLevel__PeriodicStatus2.hpp
rev/trampolines/rev__detached__DetachedEncoderLowLevel__PeriodicStatus3.hpp
rev/trampolines/rev__detached__DetachedEncoderLowLevel__PeriodicStatus4.hpp
rev/trampolines/rev__detached__DetachedEncoderSim.hpp
rev/trampolines/rev__detached__DetachedEncoder__Faults.hpp
rev/trampolines/rev__detached__SignalsConfig.hpp
rev/trampolines/rev__detached__SplineEncoder.hpp
rev/trampolines/rev__servohub__ServoChannel.hpp
rev/trampolines/rev__servohub__ServoChannelConfig.hpp
rev/trampolines/rev__servohub__ServoChannelConfigAccessor.hpp
rev/trampolines/rev__servohub__ServoChannelConfig__PulseRange_t.hpp
rev/trampolines/rev__servohub__ServoHub.hpp
rev/trampolines/rev__servohub__ServoHubConfig.hpp
rev/trampolines/rev__servohub__ServoHubConfigAccessor.hpp
rev/trampolines/rev__servohub__ServoHubLowLevel.hpp
rev/trampolines/rev__servohub__ServoHubLowLevel__FirmwareVersion.hpp
robotpy_rev-2026.0.1.dist-info/METADATA
robotpy_rev-2026.0.1.dist-info/WHEEL
robotpy_rev-2026.0.1.dist-info/entry_points.txt
robotpy_rev-2026.0.1.dist-info/licenses/LICENSE
robotpy_rev-2026.0.1.dist-info/RECORD
