Metadata-Version: 2.4
Name: robotpy-rev
Version: 2026.0.1
Summary: REVLib for RobotPy
Project-URL: Source code, https://github.com/robotpy/robotpy-rev
Author-email: RobotPy Development Team <robotpy@googlegroups.com>
License-Expression: BSD-3-Clause
License-File: LICENSE
Requires-Dist: wpilib<2027,>=2026.1.1
